opentelemetry/instrumentation/anthropic/__init__.py
opentelemetry/instrumentation/anthropic/package.py
opentelemetry/instrumentation/anthropic/version.py
opentelemetry_instrument_anthropic-0.0.2.dist-info/METADATA
opentelemetry_instrument_anthropic-0.0.2.dist-info/WHEEL
opentelemetry_instrument_anthropic-0.0.2.dist-info/entry_points.txt
opentelemetry_instrument_anthropic-0.0.2.dist-info/RECORD
