Metadata-Version: 2.1
Name: opentelemetry-instrument-anthropic
Version: 0.0.2
Summary: Instruments Anthropic client for OpenTelemetry
Author: Frank Chen
Author-email: frxchen@gmail.com
Requires-Python: >=3.7.1,<4.0
Classifier: Programming Language :: Python :: 3
Classifier: Programming Language :: Python :: 3.8
Classifier: Programming Language :: Python :: 3.9
Classifier: Programming Language :: Python :: 3.10
Classifier: Programming Language :: Python :: 3.11
Provides-Extra: instruments
Requires-Dist: anthropic (==0.3.8) ; extra == "instruments"
Requires-Dist: opentelemetry-api (>=1.18.0,<1.19.0)
Requires-Dist: opentelemetry-instrumentation (==0.39b)
Requires-Dist: opentelemetry-semantic-conventions (>=0.39b0,<1.0)
Requires-Dist: opentelemetry-test-utils (>=0.39b0,<1.0)
Requires-Dist: wrapt (>=1.15.0,<2.0.0)
